<?xml version="1.0" encoding="utf-8" ?><dwsync><file name="core_paths.html" server="stage2.curran-connors.com//httpdocs/emj/emj-dev/" local="3490703093" remote="12080125892" Dst="-1" /><file name="functions.html" server="stage2.curran-connors.com//httpdocs/emj/emj-dev/" local="3490703093" remote="12080125892" Dst="-1" /><file name="index.html" server="stage2.curran-connors.com//httpdocs/emj/emj-dev/" local="3490703093" remote="12076671332" Dst="-1" /><file name="initialize.html" server="stage2.curran-connors.com//httpdocs/emj/emj-dev/" local="3490703094" remote="12080125892" Dst="-1" /><file name="nav_constants.html" server="stage2.curran-connors.com//httpdocs/emj/emj-dev/" local="3490703094" remote="12080125892" Dst="-1" /><file name="plugins.html" server="stage2.curran-connors.com//httpdocs/emj/emj-dev/" local="3490703095" remote="12080125892" Dst="-1" /><file name="product_arrays.html" server="stage2.curran-connors.com//httpdocs/emj/emj-dev/" local="3490703095" remote="12080125892" Dst="-1" /><file name="timthumb.html" server="stage2.curran-connors.com//httpdocs/emj/emj-dev/" local="3490703095" remote="12080125892" Dst="-1" /></dwsync>