<?xml version="1.0" encoding="utf-8" ?><dwsync><file name="1_color.png" server="stage2.curran-connors.com//httpdocs/emj/emj-dev/" local="3490703720" remote="12076585172" Dst="-1" /><file name="1_bw.png" server="stage2.curran-connors.com//httpdocs/emj/emj-dev/" local="3490703721" remote="12076585172" Dst="-1" /><file name="1.png" server="stage2.curran-connors.com//httpdocs/emj/emj-dev/" local="3490703721" remote="12076585172" Dst="-1" /><file name="2_bw.png" server="stage2.curran-connors.com//httpdocs/emj/emj-dev/" local="3490703722" remote="12076585172" Dst="-1" /><file name="2_color.png" server="stage2.curran-connors.com//httpdocs/emj/emj-dev/" local="3490703722" remote="12076585172" Dst="-1" /><file name="2.png" server="stage2.curran-connors.com//httpdocs/emj/emj-dev/" local="3490703723" remote="12076585172" Dst="-1" /><file name="3_bw.png" server="stage2.curran-connors.com//httpdocs/emj/emj-dev/" local="3490703723" remote="12076585172" Dst="-1" /><file name="3_color.png" server="stage2.curran-connors.com//httpdocs/emj/emj-dev/" local="3490703723" remote="12076585172" Dst="-1" /><file name="3.png" server="stage2.curran-connors.com//httpdocs/emj/emj-dev/" local="3490703724" remote="12076585172" Dst="-1" /></dwsync>